Metadata-Version: 2.1
Name: spacy-data-debug
Version: 0.0.3
Summary: spaCy Data Debug has utilities to help you debug your custom NER data. It checks for inconsistencies in labels for the same text.
Home-page: https://github.com/kabirkhan/spacy_data_debug
Author: Kabir Khan
Author-email: kakh@microsoft.com
License: Apache Software License 2.0
Keywords: spacy,data,machine learning,nlp,natural language processing,ner,named entity recognition
Platform: UNKNOWN
Classifier: Development Status :: 3 - Alpha
Classifier: Intended Audience :: Developers
Classifier: License :: OSI Approved :: Apache Software License
Classifier: Natural Language :: English
Classifier: Programming Language :: Python :: 3.6
Classifier: Programming Language :: Python :: 3.7
Classifier: Programming Language :: Python :: 3.8
Requires-Python: >=3.6
